[
  {
    "name": "chatwire-apprise",
    "pypi": "chatwire-apprise",
    "description": "Push notifications to ntfy, Slack, Discord, Pushover, and 80+ services via Apprise.",
    "author": "allenbina",
    "signed": true,
    "homepage": "https://github.com/allenbina/chatwire-apprise",
    "icon": "📣",
    "tags": ["action"]
  },
  {
    "name": "chatwire-telegram",
    "pypi": "chatwire-telegram",
    "description": "Relay iMessages to and from a Telegram bot. Two-way bridge with full group chat support.",
    "author": "allenbina",
    "signed": true,
    "homepage": "https://github.com/allenbina/chatwire-telegram",
    "icon": "💬",
    "tags": ["bridge"]
  },
  {
    "name": "chatwire-webhook",
    "pypi": "chatwire-webhook",
    "description": "POST every inbound iMessage to a webhook URL. Build automations with Zapier, n8n, and anything that speaks HTTP.",
    "author": "allenbina",
    "signed": true,
    "homepage": "https://github.com/allenbina/chatwire-webhook",
    "icon": "🔗",
    "tags": ["action"]
  },
  {
    "name": "chatwire-stats",
    "pypi": "chatwire-stats",
    "description": "Message statistics dashboard — charts for message volume, response times, and top contacts.",
    "author": "allenbina",
    "signed": true,
    "homepage": "https://github.com/allenbina/chatwire-stats",
    "icon": "📊",
    "tags": ["ui", "official"]
  },
  {
    "name": "chatwire-theme-rosepine",
    "pypi": "chatwire-theme-rosepine",
    "description": "Rosé Pine color family — three variants: base (dark), Moon (dark), and Dawn (light).",
    "author": "allenbina",
    "signed": true,
    "homepage": "https://github.com/allenbina/chatwire-theme-rosepine",
    "icon": "🎨",
    "tags": ["ui", "theme"]
  },
  {
    "name": "chatwire-example",
    "pypi": "chatwire-example",
    "description": "Example plugin for testing install/uninstall. Does nothing.",
    "author": "allenbina",
    "signed": false,
    "homepage": "https://github.com/allenbina/chatwire-example",
    "icon": "🧪",
    "tags": ["ui"]
  },
  {
    "name": "chatwire-mqtt",
    "pypi": "chatwire-mqtt",
    "description": "Publish every inbound iMessage to an MQTT broker. Integrates with Home Assistant, Node-RED, OpenHAB, and any MQTT subscriber.",
    "author": "allenbina",
    "signed": true,
    "homepage": "https://github.com/allenbina/chatwire-mqtt",
    "icon": "📡",
    "tags": ["action"]
  },
  {
    "name": "chatwire-ha",
    "pypi": "chatwire-ha",
    "description": "Control Home Assistant automations, scenes, and services by typing keywords into iMessage.",
    "author": "allenbina",
    "signed": true,
    "homepage": "https://github.com/allenbina/chatwire-ha",
    "icon": "🏠",
    "tags": ["action"]
  },
  {
    "name": "chatwire-xmpp",
    "pypi": "chatwire-xmpp",
    "description": "Bridge iMessage ↔ XMPP (Jabber) for whitelisted contacts. Two-way relay via slixmpp.",
    "author": "allenbina",
    "signed": true,
    "homepage": "https://github.com/allenbina/chatwire-xmpp",
    "icon": "💬",
    "tags": ["bridge"]
  }
]
